{
  "display": {
    "description": {
      "text": "Has obtenido Vanishing curse I",
      "color": "yellow"
    },
    "title": {
      "text": " Vanishing curse I",
      "color": "white"
    },
    "icon": {
      "item": "minecraft:enchanted_book"
    },
      "frame": "goal",
      "show_toast": true,
      "announce_to_chat": true,
      "hidden": false
  },
  "criteria": {
    "item": {
      "trigger": "minecraft:inventory_changed",
      "conditions":{
				"items": [
					{
						"enchantments": [
							{
								"enchantment": "minecraft:vanishing_curse",
								"levels":1
							}
						]
					}
				]
			}
    }
  },
  "rewards": {
    "function": "function:librosencantados/vanishing_curse-1"
  },
  "parent": "fullitem:librosencantados/root"
}