{
  "display": {
    "description": {
      "text": "Has obtenido Oak trapdoor.",
      "color": "yellow"
    },
    "title": {
      "text": " Oak trapdoor ",
      "color": "white"
    },
    "icon": {
      "item": "minecraft:oak_trapdoor"
    },
      "frame": "goal",
      "show_toast": true,
      "announce_to_chat": true,
      "hidden": false
  },
  "criteria": {
    "stone": {
      "trigger": "minecraft:inventory_changed",
      "conditions": {
        "items": [
          {
            "item": "minecraft:oak_trapdoor"
          }
        ]
      }
    }
  },
  "rewards": {
    "function": "function:redstone/oak_trapdoor"
  },
  "parent": "fullitem:redstone/root"
}